setup.py
raven_django_newauth/__init__.py
raven_django_newauth/client.py
raven_django_newauth.egg-info/PKG-INFO
raven_django_newauth.egg-info/SOURCES.txt
raven_django_newauth.egg-info/dependency_links.txt
raven_django_newauth.egg-info/requires.txt
raven_django_newauth.egg-info/top_level.txt