Metadata-Version: 1.1
Name: raven-django-newauth
Version: 0.0.1
Summary: Sentry client for django application using django-newauth.
Home-page: https://github.com/hirokiky/raven-django-newauth/
Author: Hiroki KIYOHARA
Author-email: hirokiky@gmail.com
License: MIT License
Platform: UNKNOWN
Classifier: Development Status :: 1 - Planning
Classifier: Environment :: Plugins
Classifier: Framework :: Django
Classifier: Intended Audience :: Developers
Classifier: License :: OSI Approved :: MIT License
Classifier: Programming Language :: Python
Classifier: Topic :: Software Development :: Libraries :: Python Modules
